stein_tools/__init__.py
stein_tools/example.py
stein_tools-0.0.1.dist-info/METADATA
stein_tools-0.0.1.dist-info/WHEEL
stein_tools-0.0.1.dist-info/licenses/LICENSE
stein_tools-0.0.1.dist-info/RECORD
